dhttp/__init__.py
dhttp/__main__.py
dhttp/dhttpversion.py
dhttp/sslcert.py
dhttp/tcp.py
dhttp/ws.py
dhttp-1.3.3.dist-info/LICENSE
dhttp-1.3.3.dist-info/METADATA
dhttp-1.3.3.dist-info/WHEEL
dhttp-1.3.3.dist-info/top_level.txt
dhttp-1.3.3.dist-info/RECORD
