Metadata-Version: 2.1
Name: dhttp
Version: 1.3.3
Summary: A simple, dynamic, decorator-based HTTP server inspired by Node.js's Express. Supports trio, TLS and WebSockets.
Home-page: UNKNOWN
Author: Gustavo Rehermann
Author-email: rehermann6046@gmail.com
License: MIT
Keywords: http server httpd express decorator simple easy dynamic trio tls ssl websocket websockets
Platform: UNKNOWN
Classifier: Topic :: Internet :: WWW/HTTP :: HTTP Servers
Classifier: License :: OSI Approved :: MIT License
Requires-Dist: trio (==0.11.0)
Requires-Dist: typing (==3.6.6)
Requires-Dist: Jinja2 (==2.10)
Requires-Dist: setuptools (==39.0.1)
Requires-Dist: pyOpenSSL (==19.0.0)
